profanity_hinglish/__init__.py
profanity_hinglish/block_words
profanity_hinglish/profanity.py
profanity_hinglish-0.1.5.dist-info/licenses/LICENSE
profanity_hinglish-0.1.5.dist-info/METADATA
profanity_hinglish-0.1.5.dist-info/WHEEL
profanity_hinglish-0.1.5.dist-info/RECORD
